AUTHORS.rst
CONTRIBUTING.rst
HISTORY.rst
LICENSE
MANIFEST.in
README.rst
setup.py
jsonhumanize/__init__.py
jsonhumanize/jsonhumanize.py
jsonhumanize.egg-info/PKG-INFO
jsonhumanize.egg-info/SOURCES.txt
jsonhumanize.egg-info/dependency_links.txt
jsonhumanize.egg-info/entry_points.txt
jsonhumanize.egg-info/not-zip-safe
jsonhumanize.egg-info/requires.txt
jsonhumanize.egg-info/top_level.txt