Metadata-Version: 1.1
Name: jsonhumanize
Version: 0.1.1
Summary: Convert JSON to human readable HTML
Home-page: https://github.com/magarcia/jsonhumanize
Author: Martin Garcia
Author-email: newluxfero@gmail.com
License: MIT
Keywords: jsonhumanize
Platform: UNKNOWN
Classifier: Development Status :: 2 - Pre-Alpha
Classifier: Intended Audience :: Developers
Classifier: License :: OSI Approved :: MIT License
Classifier: Natural Language :: English
Classifier: Programming Language :: Python :: 2
Classifier: Programming Language :: Python :: 2.6
Classifier: Programming Language :: Python :: 2.7
Classifier: Programming Language :: Python :: 3
Classifier: Programming Language :: Python :: 3.3
